<data>

	
<level id="1" name="knock off" displayname="undefined" category="0" desc="" bg="2" >
	<soccerballs gold="2" fail="6" />
	<objgroup name="">
		<obj id="" type="parrot" x="515" y="358" rot="0" scale="1" params="game_layer=NormalObjects_Nearer,editor_layer=1,fixed=false" />
		<obj id="" type="parrot" x="109" y="304" rot="0" scale="1" params="game_layer=NormalObjects_Nearer,editor_layer=1,fixed=false" />
		<obj id="" type="flying_parrot" x="-71" y="5" rot="0" scale="1" params="game_layer=NormalObjects_Nearer,editor_layer=1,fixed=false" />
		<obj id="" type="flying_parrot" x="-115" y="92" rot="0" scale="1" params="game_layer=NormalObjects_Nearer,editor_layer=1,fixed=false" />
		<obj id="" type="flying_parrot" x="-131" y="176" rot="0" scale="1" params="game_layer=NormalObjects_Nearer,editor_layer=1,fixed=false" />
	</objgroup>
	<objgroup name="soccerballs">
		<obj id="" type="player" x="286" y="428" rot="0" scale="1" params="game_layer=Centre,editor_layer=1,fixed=true" />
		<obj id="" type="referee" x="476" y="484" rot="0" scale="1" params="game_layer=Centre,editor_layer=1,fixed=true" />
		<obj id="" type="ball_normal" x="306" y="421" rot="0" scale="1" params="game_layer=Centre,editor_layer=1,fixed=false" />
		<obj id="" type="goal2" x="764" y="365" rot="0" scale="1" params="game_layer=NormalObjects,editor_layer=1,fixed=true" />
		<obj id="uid_236379" type="metalpost_loose" x="445" y="367" rot="89.89158511750149" scale="1" params="game_layer=Centre,editor_layer=1,fixed=false" />
		<obj id="uid_627870" type="metalpost_loose" x="504" y="367" rot="89.89158511750149" scale="1" params="game_layer=Centre,editor_layer=1,fixed=false" />
		<obj id="" type="player" x="636" y="373" rot="0" scale="1" params="game_layer=Centre,editor_layer=1,fixed=true" />
		<obj id="" type="referee" x="94" y="417" rot="0" scale="1" params="game_layer=Centre,editor_layer=1,fixed=true" />
		<obj id="uid_173323" type="metalpost_loose" x="147" y="403" rot="0" scale="1" params="game_layer=Centre,editor_layer=1,fixed=false" />
		<obj id="uid_279418" type="metalpost_loose" x="147" y="344" rot="0" scale="1" params="game_layer=Centre,editor_layer=1,fixed=false" />
		<obj id="uid_388877" type="metalpost_loose" x="144" y="307" rot="89.53539062730914" scale="1" params="game_layer=Centre,editor_layer=1,fixed=false" />
		<obj id="uid_586654" type="metalpost_loose" x="85" y="307" rot="89.53539062730916" scale="1" params="game_layer=Centre,editor_layer=1,fixed=false" />
	</objgroup>
	<objgroup name="normal">
		<obj id="uid_581250" type="switch_once" x="537" y="386" rot="0" scale="1" params="game_layer=NormalObjects,editor_layer=1,fixed=true" />
		<obj id="" type="hinge" x="56" y="308" rot="0" scale="1" params="game_layer=Decorations,editor_layer=1,fixed=true" />
	</objgroup>
	<objgroup name="platform">
		<obj id="uid_776943" type="path_object" x="65" y="209" rot="0" scale="1" params="path_startmode=stop,path_endmode=stop,path_switchmode=start,path_line=uid_980932,path_speed=1,path_ease=linear,path_easevalue=1,path_startpos=0,path_rotatetopath=false,editor_layer=1,game_layer=Centre,fixed=true" />
	</objgroup>
	<joints>
		<joint type="weld" id="" objid0="uid_236379" objid1="uid_627870" params="collide_joined=false,weld_soft=true,weld_soft_frequency=100" />
		<joint type="weld" id="" objid0="uid_279418" objid1="uid_173323" params="collide_joined=false,weld_soft=false,weld_soft_frequency=0.5" />
		<joint type="weld" id="" objid0="uid_279418" objid1="uid_388877" params="collide_joined=false,weld_soft=false,weld_soft_frequency=0.5" />
		<joint type="weld" id="" objid0="uid_586654" objid1="uid_388877" params="collide_joined=false,weld_soft=false,weld_soft_frequency=0.5" />
		<joint type="rev" id="" objid0="uid_934674" objid1="uid_586654" x="56" y="307" params="collide_joined=false,rev_soft=false,rev_soft_frequency=0.5,rev_enablelimit=false,rev_lowerangle=0,rev_upperangle=0,rev_enablemotor=false,rev_motorrate=0,rev_motorratio=0,rev_motormax=10000,joint_initfunction=InitJoint_RotateSwitch" />
		<joint type="dist" id="" objid0="uid_776943" objid1="uid_388877" x0="78" y0="220" x1="160" y1="305" params="collide_joined=false,dist_soft=true,dist_soft_frequency=0.9,dist_limit=0,joint_initfunction=InitGameObjJoint_Null" />
		<joint type="weld" id="" objid0="uid_586654" objid1="uid_279418" params="collide_joined=false,weld_soft=false,weld_soft_frequency=0.5" />
		<joint type="weld" id="" objid0="uid_586654" objid1="uid_173323" params="collide_joined=false,weld_soft=false,weld_soft_frequency=0.5" />
		<joint type="weld" id="" objid0="uid_388877" objid1="uid_279418" params="collide_joined=false,weld_soft=false,weld_soft_frequency=0.5" />
		<joint type="weld" id="" objid0="uid_388877" objid1="uid_173323" params="collide_joined=false,weld_soft=false,weld_soft_frequency=0.5" />
		<joint type="logic" id="" objid0="uid_581250" objid1="uid_776943" params="" />
	</joints>
<line type="0" id="uid_934674" params="editor_layer=1,game_layer=Centre,line_material=poly_collide_grass,line_spline=false" >
<points a="-126,286, 54,281, 55,359, 87,416, 143,433, 184,433, 184,433, 322,431, 350,431, 388,429" />
<points a="395,421, 396,397, 408,377, 434,377, 441,394, 432,414, 437,477, 468,490, 507,494, 520,467" />
<points a="517,426, 514,379, 528,375, 541,445, 564,448, 571,414, 565,387, 656,375, 714,366, 792,366" />
<points a="825,305, 898,215, 974,264, 993,628, -104,652" />
</line>
<line type="0" id="uid_980932" params="editor_layer=1,game_layer=Centre,line_material=poly_path,line_spline=false" >
<points a="68,210, 42,119" />
</line>
<map minx="0" maxx="0" miny="0" maxy="0" cellw="16" cellh="16" >
<mapdata a=""/>
</map>
</level>
	
	
<level id="1" name="Basic Level 1" displayname="undefined" category="0" desc="" bg="2" >
	<soccerballs gold="2" fail="6" />
	<objgroup name="soccerballs">
		<obj id="" type="player" x="329" y="421" rot="0" scale="1" params="game_layer=Centre,editor_layer=1,game_layer=Centre,fixed=true" />
		<obj id="" type="referee" x="127" y="422" rot="0" scale="1" params="game_layer=Centre,editor_layer=1,game_layer=Centre,fixed=true" />
		<obj id="" type="goal2" x="612" y="427" rot="0" scale="1" params="game_layer=Centre,editor_layer=1,game_layer=Centre,fixed=true" />
		<obj id="" type="ball_normal" x="344" y="414" rot="0" scale="1" params="game_layer=Centre,editor_layer=1,game_layer=Centre,fixed=false" />
		<obj id="uid_860629" type="metalpost_loose" x="576" y="396" rot="0" scale="1" params="game_layer=Centre,editor_layer=1,game_layer=Centre,fixed=false" />
		<obj id="uid_223278" type="metalpost_loose" x="576" y="337" rot="0" scale="1" params="game_layer=Centre,editor_layer=1,game_layer=Centre,fixed=false" />
	</objgroup>
	<objgroup name="platform">
		<obj id="uid_412873" type="path_object" x="576" y="298" rot="0" scale="1" params="path_startmode=stop,path_endmode=stop,path_switchmode=start,path_line=uid_117857,path_speed=2,path_ease=linear,path_easevalue=1,path_startpos=0,path_rotatetopath=false,editor_layer=1,game_layer=Centre,fixed=true" />
	</objgroup>
	<objgroup name="links">
		<obj id="" type="helptext_text" x="342" y="122" rot="0" scale="1.6800000000000006" params="game_layer=Centre,helptext_text=Soccer Balls 2,helptext_initialdelay=0,editor_layer=1,game_layer=Centre" />
		<obj id="" type="helptext_text" x="141" y="240" rot="0" scale="1" params="game_layer=Centre,helptext_text=Knock over refs,helptext_initialdelay=2,editor_layer=1,game_layer=Centre" />
		<obj id="uid_630107" type="helptext_text" x="521" y="248" rot="0" scale="1" params="game_layer=Centre,helptext_text=and score goals.,helptext_initialdelay=1,editor_layer=1,game_layer=Centre" />
	</objgroup>
	<joints>
		<joint type="weld" id="" objid0="uid_223278" objid1="uid_412873" params="collide_joined=false,weld_soft=false,weld_soft_frequency=0.5" />
		<joint type="weld" id="" objid0="uid_860629" objid1="uid_412873" params="collide_joined=false,weld_soft=false,weld_soft_frequency=0.5" />
		<joint type="logic" id="" objid0="uid_973482" objid1="uid_412873" params="" />
		<joint type="logic" id="" objid0="uid_973482" objid1="uid_630107" params="" />
	</joints>
<line type="0" id="" params="editor_layer=1,game_layer=Centre,line_material=poly_collide_grass,line_spline=false" >
<points a="-21,209, 39,215, 70,422, 644,427, 698,402, 755,218, 942,213, 948,760, -184,705, -179,243" />
</line>
<line type="0" id="" params="editor_layer=1,game_layer=Centre,line_material=poly_scrollarea,line_spline=false" >
<points a="-54,0, 849,6, 865,598, -60,589" />
</line>
<line type="0" id="uid_973482" params="editor_layer=1,game_layer=Centre,line_material=poly_switch,line_spline=false" >
<points a="78,418, 73,336, 152,336, 155,421" />
</line>
<line type="0" id="uid_117857" params="editor_layer=1,game_layer=Centre,line_material=poly_path,line_spline=false" >
<points a="576,298, 577,-163" />
</line>
<line type="0" id="" params="editor_layer=1,game_layer=Near_Foreground,line_material=poly_collide_mud,line_spline=false" >
<points a="146,541, 314,499, 447,500, 645,488, 754,443, 915,390, 1075,393, 1058,713, 83,704" />
</line>
<map minx="0" maxx="0" miny="0" maxy="0" cellw="16" cellh="16" >
<mapdata a=""/>
</map>
</level>
	


</data>